Metadata-Version: 1.1
Name: django-zipkin-trace-nonspecialist
Version: 1.1.2
Summary: Automatically trace your Django application to Zipkin
Home-page: https://github.com/nonspecialist/django-zipkin-trace
Author: Colin Panisset
Author-email: github@clabber.com
License: MIT
Platform: UNKNOWN
Classifier: Development Status :: 5 - Production/Stable
Classifier: Environment :: Web Environment
Classifier: Framework :: Django
Classifier: Intended Audience :: Developers
Classifier: License :: OSI Approved :: MIT License
Classifier: Operating System :: OS Independent
Classifier: Programming Language :: Python
Classifier: Programming Language :: Python :: 2.7
Classifier: Programming Language :: Python :: 3
Classifier: Programming Language :: Python :: 3.4
Classifier: Programming Language :: Python :: 3.5
Classifier: Programming Language :: Python :: 3.6
Classifier: Topic :: System :: Networking :: Monitoring
